parallel_ssh-2.16.0.post1.dist-info/licenses/COPYING
parallel_ssh-2.16.0.post1.dist-info/licenses/COPYING.LESSER
parallel_ssh-2.16.0.post1.dist-info/licenses/LICENSE
pssh/__init__.py
pssh/_version.py
pssh/config.py
pssh/constants.py
pssh/exceptions.py
pssh/output.py
pssh/utils.py
pssh/clients/__init__.py
pssh/clients/common.py
pssh/clients/reader.py
pssh/clients/base/__init__.py
pssh/clients/base/parallel.py
pssh/clients/base/single.py
pssh/clients/native/__init__.py
pssh/clients/native/parallel.py
pssh/clients/native/single.py
pssh/clients/native/tunnel.py
pssh/clients/ssh/__init__.py
pssh/clients/ssh/parallel.py
pssh/clients/ssh/single.py
parallel_ssh-2.16.0.post1.dist-info/METADATA
parallel_ssh-2.16.0.post1.dist-info/WHEEL
parallel_ssh-2.16.0.post1.dist-info/top_level.txt
parallel_ssh-2.16.0.post1.dist-info/RECORD
